odoo10_addon_sale_layout_multi_company-10.0.1.0.0.99.dev3-py2.7-nspkg.pth
odoo/addons/sale_layout_multi_company/README.rst
odoo/addons/sale_layout_multi_company/__init__.py
odoo/addons/sale_layout_multi_company/__manifest__.py
odoo/addons/sale_layout_multi_company/i18n/de.po
odoo/addons/sale_layout_multi_company/i18n/es.po
odoo/addons/sale_layout_multi_company/i18n/fr.po
odoo/addons/sale_layout_multi_company/i18n/sale_layout_multi_company.pot
odoo/addons/sale_layout_multi_company/i18n/sl.po
odoo/addons/sale_layout_multi_company/i18n/zh_CN.po
odoo/addons/sale_layout_multi_company/models/__init__.py
odoo/addons/sale_layout_multi_company/models/sale_layout.py
odoo/addons/sale_layout_multi_company/security/record_rules.xml
odoo/addons/sale_layout_multi_company/static/description/icon.png
odoo/addons/sale_layout_multi_company/views/sale_layout_view.xml
odoo10_addon_sale_layout_multi_company-10.0.1.0.0.99.dev3.dist-info/DESCRIPTION.rst
odoo10_addon_sale_layout_multi_company-10.0.1.0.0.99.dev3.dist-info/METADATA
odoo10_addon_sale_layout_multi_company-10.0.1.0.0.99.dev3.dist-info/RECORD
odoo10_addon_sale_layout_multi_company-10.0.1.0.0.99.dev3.dist-info/WHEEL
odoo10_addon_sale_layout_multi_company-10.0.1.0.0.99.dev3.dist-info/metadata.json
odoo10_addon_sale_layout_multi_company-10.0.1.0.0.99.dev3.dist-info/namespace_packages.txt
odoo10_addon_sale_layout_multi_company-10.0.1.0.0.99.dev3.dist-info/top_level.txt
