Metadata-Version: 2.0
Name: odoo10-addon-sale-layout-multi-company
Version: 10.0.1.0.0.99.dev3
Summary: Multi company features for sale_layout
Home-page: https://github.com/OCA/multi-company/tree/10.0/sale_layout_multi_company
Author: Agile Business Group, Odoo Community Association (OCA)
Author-email: support@odoo-community.org
License: AGPL-3
Platform: UNKNOWN
Classifier: Programming Language :: Python
Classifier: Framework :: Odoo
Classifier: License :: OSI Approved :: GNU Affero General Public License v3
Requires-Python: ~=2.7
Requires-Dist: odoo (<10.1dev,>=10.0)
Requires-Dist: odoo10-addon-base-multi-company
